ggsipu_result/__init__.py
ggsipu_result/data_process.py
ggsipu_result/objects.py
ggsipu_result/util.py
ggsipu_result-0.3.3.dist-info/LICENSE
ggsipu_result-0.3.3.dist-info/METADATA
ggsipu_result-0.3.3.dist-info/WHEEL
ggsipu_result-0.3.3.dist-info/top_level.txt
ggsipu_result-0.3.3.dist-info/RECORD
