Metadata-Version: 2.1
Name: ggsipu-result
Version: 0.3.3
Summary: GGSIPU Results PDF parser and analyzer
Home-page: https://github.com/ashutoshvarma/ggsipu_result
Author: Ashutosh Varma
Author-email: ashutoshvarma11@live.com
License: UNKNOWN
Keywords: ggsipu result,ipu result converter,cgpa calculator
Platform: UNKNOWN
Classifier: Programming Language :: Python
Classifier: Programming Language :: Python :: 3.4
Classifier: Programming Language :: Python :: 3.5
Classifier: Programming Language :: Python :: 3.6
Classifier: Programming Language :: Python :: 3 :: Only
Classifier: Development Status :: 5 - Production/Stable
Classifier: License :: OSI Approved :: GNU General Public License v3 (GPLv3)
Classifier: Topic :: Text Processing
Requires-Python: >=3.4
Requires-Dist: pyxpdf (>=0.2.1)
